treams_ebeam/__init__.py
treams_ebeam/illumination.py
treams_ebeam/observables.py
treams_ebeam/observables_cylindrical.py
treams_ebeam/observables_spherical.py
treams_ebeam-0.1.3.dist-info/METADATA
treams_ebeam-0.1.3.dist-info/WHEEL
treams_ebeam-0.1.3.dist-info/RECORD
