Metadata-Version: 2.4
Name: treams-ebeam
Version: 0.1.3
Summary: A Extension to treams to work with electron beams
Author-email: Elli Stamatopoulou <panagiota.stamatopoulou@kit.edu>
Requires-Python: >=3.10
Requires-Dist: numpy>=2.2.6
Requires-Dist: scipy>=1.15.3
Requires-Dist: treams>=0.4.5
